perforatedai/__init__.cpython-312-darwin.so
perforatedai/blockwise_perforatedai.cpython-312-darwin.so
perforatedai/clean_perforatedai.cpython-312-darwin.so
perforatedai/globals_perforatedai.cpython-312-darwin.so
perforatedai/library_perforatedai.cpython-312-darwin.so
perforatedai/modules_perforatedai.cpython-312-darwin.so
perforatedai/tracker_perforatedai.cpython-312-darwin.so
perforatedai/utils_perforatedai.cpython-312-darwin.so
perforatedai-3.0.7.dist-info/METADATA
perforatedai-3.0.7.dist-info/WHEEL
perforatedai-3.0.7.dist-info/top_level.txt
perforatedai-3.0.7.dist-info/RECORD
