Metadata-Version: 2.4
Name: perforatedai
Version: 3.0.7
Summary: perforatedai perforatedai package
Author: PerforatedAI
Author-email: rorry@perforatedai.com
License: Apache 2.0
Requires-Python: >=3.6
Requires-Dist: torch
Requires-Dist: torchvision
Requires-Dist: matplotlib
Requires-Dist: pandas
Requires-Dist: rsa
Requires-Dist: pyyaml
Requires-Dist: safetensors
Dynamic: author
Dynamic: author-email
Dynamic: license
Dynamic: requires-dist
Dynamic: requires-python
Dynamic: summary
